fastpubsub/__about__.py
fastpubsub/__init__.py
fastpubsub/__main__.py
fastpubsub/applications.py
fastpubsub/broker.py
fastpubsub/builder.py
fastpubsub/cli/__init__.py
fastpubsub/cli/main.py
fastpubsub/cli/options.py
fastpubsub/cli/runner.py
fastpubsub/cli/utils.py
fastpubsub/clients/__init__.py
fastpubsub/clients/factory.py
fastpubsub/clients/pubsub.py
fastpubsub/clients/scheduler.py
fastpubsub/concurrency/__init__.py
fastpubsub/concurrency/manager.py
fastpubsub/concurrency/tasks.py
fastpubsub/concurrency/utils.py
fastpubsub/datastructures.py
fastpubsub/exceptions.py
fastpubsub/logger.py
fastpubsub/middlewares/__init__.py
fastpubsub/middlewares/base.py
fastpubsub/middlewares/di.py
fastpubsub/middlewares/gzip.py
fastpubsub/pubsub/__init__.py
fastpubsub/pubsub/publisher.py
fastpubsub/pubsub/subscriber.py
fastpubsub/py.typed
fastpubsub/router.py
fastpubsub/testing.py
fastpubsub/types.py
fastpubsub-0.8.1.dist-info/licenses/LICENSE
fastpubsub-0.8.1.dist-info/WHEEL
fastpubsub-0.8.1.dist-info/entry_points.txt
fastpubsub-0.8.1.dist-info/METADATA
fastpubsub-0.8.1.dist-info/RECORD
