Metadata-Version: 2.4
Name: fastpubsub
Version: 0.8.1
Summary: FastPubSub: A high performance FastAPI-based message consumer framework for Google PubSub applications
Author: Sandro Matheus Vila Nova Marques
Author-email: Sandro Matheus Vila Nova Marques <sandro-matheus@hotmail.com>
License-Expression: Apache-2.0
License-File: LICENSE
Classifier: Development Status :: 4 - Beta
Classifier: License :: OSI Approved :: Apache Software License
Classifier: Programming Language :: Python
Classifier: Programming Language :: Python :: Implementation :: CPython
Classifier: Programming Language :: Python :: 3
Classifier: Programming Language :: Python :: 3 :: Only
Classifier: Programming Language :: Python :: 3.12
Classifier: Programming Language :: Python :: 3.13
Classifier: Programming Language :: Python :: 3.14
Classifier: Operating System :: OS Independent
Classifier: Topic :: Software Development :: Libraries :: Application Frameworks
Classifier: Topic :: Software Development :: Libraries :: Python Modules
Classifier: Topic :: Software Development :: Libraries
Classifier: Topic :: Software Development
Classifier: Topic :: System :: Networking
Classifier: Topic :: System :: Distributed Computing
Classifier: Typing :: Typed
Classifier: Intended Audience :: Developers
Classifier: Intended Audience :: Information Technology
Classifier: Intended Audience :: System Administrators
Classifier: Environment :: Web Environment
Classifier: Framework :: AsyncIO
Classifier: Framework :: Pydantic
Classifier: Framework :: Pydantic :: 2
Requires-Dist: click>=8.2.1
Requires-Dist: fastapi[standard-no-fastapi-cloud-cli]>=0.120.2
Requires-Dist: google-api-core>=2.25.1
Requires-Dist: google-cloud-pubsub>=2.31.1
Requires-Dist: pydantic-settings>=2.10.1
Requires-Dist: rich-toolkit>=0.15.0
Requires-Dist: typer>=0.16.0
Requires-Dist: uvicorn>=0.35.0
Requires-Python: >=3.12
